{
  "_fv": 17,
  "_type": "food",
  "definition": {
    "renderType": 0,
    "texture": "vial_of_essence",
    "customModelName": "Normal",
    "name": "Jug Of Essence",
    "rarity": "EPIC",
    "specialInfo": [],
    "creativeTab": {
      "value": "BREWING"
    },
    "stackSize": 1,
    "nutritionalValue": 6,
    "saturation": 0.30000001192092896,
    "eatingSpeed": 32,
    "resultItem": {
      "value": ""
    },
    "forDogs": false,
    "isAlwaysEdible": true,
    "animation": "drink",
    "hasGlow": true,
    "onEaten": {
      "name": "PermHealthDrink"
    }
  }
}